karddex_scanner/__init__.py
karddex_scanner/scanner.py
karddex_scanner-0.1.1.dist-info/METADATA
karddex_scanner-0.1.1.dist-info/WHEEL
karddex_scanner-0.1.1.dist-info/RECORD
