Metadata-Version: 2.3
Name: karddex-scanner
Version: 0.1.1
Summary: Biblioteca para extrair dados estruturados de cartas Pokémon via OpenAI a partir de JSON de OCR.
License: MIT
Author: Seu Nome
Author-email: luiz.juventi@karddex.com
Requires-Python: >=3.9,<4.0
Classifier: License :: OSI Approved :: MIT License
Classifier: Programming Language :: Python :: 3
Classifier: Programming Language :: Python :: 3.9
Classifier: Programming Language :: Python :: 3.10
Classifier: Programming Language :: Python :: 3.11
Classifier: Programming Language :: Python :: 3.12
Classifier: Programming Language :: Python :: 3.13
Requires-Dist: openai (>=0.27.0,<0.28.0)
